jumpstarter_driver_can/__init__.py
jumpstarter_driver_can/client.py
jumpstarter_driver_can/client_test.py
jumpstarter_driver_can/common.py
jumpstarter_driver_can/driver.py
jumpstarter_driver_can/py.typed
jumpstarter_driver_can-0.7.4.dist-info/METADATA
jumpstarter_driver_can-0.7.4.dist-info/WHEEL
jumpstarter_driver_can-0.7.4.dist-info/entry_points.txt
jumpstarter_driver_can-0.7.4.dist-info/RECORD
